[
    {
        "application":"loginwindow",
        "duration":7040,
        "starttime":"07:00:00"
    },
    {
        "application":"Chrome",
        "duration":115,
        "starttime":"08:57:20"
    },
    {
        "application":"Outlook",
        "duration":60,
        "starttime":"08:59:15"
    },
    {
        "application":"Word",
        "duration":10,
        "starttime":"09:00:15"
    },
    {
        "application":"Chrome",
        "duration":95,
        "starttime":"09:00:25"
    },
    {
        "application":"Slack",
        "duration":525,
        "starttime":"09:02:00"
    },
    {
        "application":"RARE",
        "duration":5,
        "starttime":"09:10:45"
    },
    {
        "application":"Slack",
        "duration":40,
        "starttime":"09:10:50"
    },
    {
        "application":"Outlook",
        "duration":45,
        "starttime":"09:11:30"
    },
    {
        "application":"Excel",
        "duration":10,
        "starttime":"09:12:15"
    },
    {
        "application":"Atom",
        "duration":5,
        "starttime":"09:12:25"
    },
    {
        "application":"Teams",
        "duration":715,
        "starttime":"09:12:30"
    },
    {
        "application":"Preview",
        "duration":20,
        "starttime":"09:24:25"
    },
    {
        "application":"Slack",
        "duration":170,
        "starttime":"09:24:45"
    },
    {
        "application":"Chrome",
        "duration":25,
        "starttime":"09:27:35"
    },
    {
        "application":"Slack",
        "duration":15,
        "starttime":"09:28:00"
    },
    {
        "application":"Teams",
        "duration":30,
        "starttime":"09:28:15"
    },
    {
        "application":"Slack",
        "duration":20,
        "starttime":"09:28:45"
    },
    {
        "application":"Atom",
        "duration":5,
        "starttime":"09:29:05"
    },
    {
        "application":"Slack",
        "duration":55,
        "starttime":"09:29:10"
    },
    {
        "application":"Chrome",
        "duration":5,
        "starttime":"09:30:05"
    },
    {
        "application":"Slack",
        "duration":695,
        "starttime":"09:30:10"
    },
    {
        "application":"loginwindow",
        "duration":55,
        "starttime":"09:41:45"
    },
    {
        "application":"Teams",
        "duration":160,
        "starttime":"09:42:40"
    },
    {
        "application":"Finder",
        "duration":35,
        "starttime":"09:45:20"
    },
    {
        "application":"Chrome",
        "duration":5,
        "starttime":"09:45:55"
    },
    {
        "application":"Outlook",
        "duration":25,
        "starttime":"09:46:00"
    },
    {
        "application":"Slack",
        "duration":20,
        "starttime":"09:46:25"
    },
    {
        "application":"Chrome",
        "duration":140,
        "starttime":"09:46:45"
    },
    {
        "application":"Teams",
        "duration":35,
        "starttime":"09:49:05"
    },
    {
        "application":"Outlook",
        "duration":165,
        "starttime":"09:49:40"
    },
    {
        "application":"Excel",
        "duration":5,
        "starttime":"09:52:25"
    },
    {
        "application":"Slack",
        "duration":10,
        "starttime":"09:52:30"
    },
    {
        "application":"Chrome",
        "duration":40,
        "starttime":"09:52:40"
    },
    {
        "application":"Outlook",
        "duration":175,
        "starttime":"09:53:20"
    },
    {
        "application":"Chrome",
        "duration":75,
        "starttime":"09:56:15"
    },
    {
        "application":"Preview",
        "duration":5,
        "starttime":"09:57:30"
    },
    {
        "application":"Finder",
        "duration":5,
        "starttime":"09:57:35"
    },
    {
        "application":"Teams",
        "duration":15,
        "starttime":"09:57:40"
    },
    {
        "application":"Chrome",
        "duration":295,
        "starttime":"09:57:55"
    },
    {
        "application":"Excel",
        "duration":5,
        "starttime":"10:02:50"
    },
    {
        "application":"loginwindow",
        "duration":795,
        "starttime":"10:02:55"
    },
    {
        "application":"Chrome",
        "duration":40,
        "starttime":"10:16:10"
    },
    {
        "application":"Preview",
        "duration":25,
        "starttime":"10:16:50"
    },
    {
        "application":"Outlook",
        "duration":305,
        "starttime":"10:17:15"
    },
    {
        "application":"Teams",
        "duration":565,
        "starttime":"10:22:20"
    },
    {
        "application":"Chrome",
        "duration":25,
        "starttime":"10:31:45"
    },
    {
        "application":"Teams",
        "duration":175,
        "starttime":"10:32:10"
    },
    {
        "application":"Chrome",
        "duration":10,
        "starttime":"10:35:05"
    },
    {
        "application":"Atom",
        "duration":30,
        "starttime":"10:35:15"
    },
    {
        "application":"Outlook",
        "duration":120,
        "starttime":"10:35:45"
    },
    {
        "application":"Preview",
        "duration":350,
        "starttime":"10:37:45"
    },
    {
        "application":"Finder",
        "duration":5,
        "starttime":"10:43:35"
    },
    {
        "application":"Teams",
        "duration":20,
        "starttime":"10:43:40"
    },
    {
        "application":"Atom",
        "duration":30,
        "starttime":"10:44:00"
    },
    {
        "application":"Chrome",
        "duration":20,
        "starttime":"10:44:30"
    },
    {
        "application":"Slack",
        "duration":5,
        "starttime":"10:44:50"
    },
    {
        "application":"Chrome",
        "duration":10,
        "starttime":"10:44:55"
    },
    {
        "application":"Atom",
        "duration":40,
        "starttime":"10:45:05"
    },
    {
        "application":"PowerPoint",
        "duration":5,
        "starttime":"10:45:45"
    },
    {
        "application":"zoom.us",
        "duration":25,
        "starttime":"10:45:50"
    },
    {
        "application":"Outlook",
        "duration":5,
        "starttime":"10:46:15"
    },
    {
        "application":"Chrome",
        "duration":20,
        "starttime":"10:46:20"
    },
    {
        "application":"Teams",
        "duration":10,
        "starttime":"10:46:40"
    },
    {
        "application":"Finder",
        "duration":15,
        "starttime":"10:46:50"
    },
    {
        "application":"Outlook",
        "duration":15,
        "starttime":"10:47:05"
    },
    {
        "application":"Finder",
        "duration":35,
        "starttime":"10:47:20"
    },
    {
        "application":"Chrome",
        "duration":190,
        "starttime":"10:47:55"
    },
    {
        "application":"Finder",
        "duration":10,
        "starttime":"10:51:05"
    },
    {
        "application":"Teams",
        "duration":350,
        "starttime":"10:51:15"
    },
    {
        "application":"Outlook",
        "duration":635,
        "starttime":"10:57:05"
    },
    {
        "application":"loginwindow",
        "duration":10,
        "starttime":"11:07:40"
    },
    {
        "application":"Teams",
        "duration":40,
        "starttime":"11:07:50"
    },
    {
        "application":"Preview",
        "duration":5,
        "starttime":"11:08:30"
    },
    {
        "application":"PowerPoint",
        "duration":15,
        "starttime":"11:08:35"
    },
    {
        "application":"Atom",
        "duration":5,
        "starttime":"11:08:50"
    },
    {
        "application":"Word",
        "duration":10,
        "starttime":"11:08:55"
    },
    {
        "application":"Chrome",
        "duration":5,
        "starttime":"11:09:05"
    },
    {
        "application":"Slack",
        "duration":30,
        "starttime":"11:09:10"
    },
    {
        "application":"Teams",
        "duration":20,
        "starttime":"11:09:40"
    },
    {
        "application":"Outlook",
        "duration":10,
        "starttime":"11:10:00"
    },
    {
        "application":"Atom",
        "duration":15,
        "starttime":"11:10:10"
    },
    {
        "application":"Word",
        "duration":30,
        "starttime":"11:10:25"
    },
    {
        "application":"loginwindow",
        "duration":115,
        "starttime":"11:10:55"
    },
    {
        "application":"Slack",
        "duration":20,
        "starttime":"11:12:50"
    },
    {
        "application":"Preview",
        "duration":5,
        "starttime":"11:13:10"
    },
    {
        "application":"RARE",
        "duration":5,
        "starttime":"11:13:15"
    },
    {
        "application":"Atom",
        "duration":40,
        "starttime":"11:13:20"
    },
    {
        "application":"Chrome",
        "duration":5,
        "starttime":"11:14:00"
    },
    {
        "application":"Outlook",
        "duration":15,
        "starttime":"11:14:05"
    },
    {
        "application":"Teams",
        "duration":65,
        "starttime":"11:14:20"
    },
    {
        "application":"Slack",
        "duration":415,
        "starttime":"11:15:25"
    },
    {
        "application":"RARE",
        "duration":20,
        "starttime":"11:22:20"
    },
    {
        "application":"Outlook",
        "duration":430,
        "starttime":"11:22:40"
    },
    {
        "application":"Chrome",
        "duration":25,
        "starttime":"11:29:50"
    },
    {
        "application":"Teams",
        "duration":15,
        "starttime":"11:30:15"
    },
    {
        "application":"Slack",
        "duration":75,
        "starttime":"11:30:30"
    },
    {
        "application":"PowerPoint",
        "duration":255,
        "starttime":"11:31:45"
    },
    {
        "application":"Outlook",
        "duration":40,
        "starttime":"11:36:00"
    },
    {
        "application":"Teams",
        "duration":10,
        "starttime":"11:36:40"
    },
    {
        "application":"RARE",
        "duration":55,
        "starttime":"11:36:50"
    },
    {
        "application":"Atom",
        "duration":80,
        "starttime":"11:37:45"
    },
    {
        "application":"Teams",
        "duration":60,
        "starttime":"11:39:05"
    },
    {
        "application":"Slack",
        "duration":75,
        "starttime":"11:40:05"
    },
    {
        "application":"Chrome",
        "duration":30,
        "starttime":"11:41:20"
    },
    {
        "application":"Teams",
        "duration":410,
        "starttime":"11:41:50"
    },
    {
        "application":"Slack",
        "duration":70,
        "starttime":"11:48:40"
    },
    {
        "application":"Chrome",
        "duration":5,
        "starttime":"11:49:50"
    },
    {
        "application":"RARE",
        "duration":60,
        "starttime":"11:49:55"
    },
    {
        "application":"Teams",
        "duration":10,
        "starttime":"11:50:55"
    },
    {
        "application":"loginwindow",
        "duration":660,
        "starttime":"11:51:05"
    },
    {
        "application":"Chrome",
        "duration":3475,
        "starttime":"12:02:05"
    },
    {
        "application":"Slack",
        "duration":5,
        "starttime":"13:00:00"
    },
    {
        "application":"Chrome",
        "duration":20,
        "starttime":"13:00:05"
    },
    {
        "application":"Atom",
        "duration":365,
        "starttime":"13:00:25"
    },
    {
        "application":"Outlook",
        "duration":50,
        "starttime":"13:06:30"
    },
    {
        "application":"Teams",
        "duration":30,
        "starttime":"13:07:20"
    },
    {
        "application":"Slack",
        "duration":240,
        "starttime":"13:07:50"
    },
    {
        "application":"Finder",
        "duration":5,
        "starttime":"13:11:50"
    },
    {
        "application":"Outlook",
        "duration":545,
        "starttime":"13:11:55"
    },
    {
        "application":"Atom",
        "duration":5,
        "starttime":"13:21:00"
    },
    {
        "application":"Outlook",
        "duration":320,
        "starttime":"13:21:05"
    },
    {
        "application":"Atom",
        "duration":5,
        "starttime":"13:26:25"
    },
    {
        "application":"Outlook",
        "duration":65,
        "starttime":"13:26:30"
    },
    {
        "application":"Chrome",
        "duration":5,
        "starttime":"13:27:35"
    },
    {
        "application":"PowerPoint",
        "duration":255,
        "starttime":"13:27:40"
    },
    {
        "application":"Atom",
        "duration":380,
        "starttime":"13:31:55"
    },
    {
        "application":"RARE",
        "duration":20,
        "starttime":"13:38:15"
    },
    {
        "application":"Outlook",
        "duration":10,
        "starttime":"13:38:35"
    },
    {
        "application":"Chrome",
        "duration":5,
        "starttime":"13:38:45"
    },
    {
        "application":"Finder",
        "duration":25,
        "starttime":"13:38:50"
    },
    {
        "application":"Atom",
        "duration":100,
        "starttime":"13:39:15"
    },
    {
        "application":"Slack",
        "duration":675,
        "starttime":"13:40:55"
    },
    {
        "application":"Atom",
        "duration":25,
        "starttime":"13:52:10"
    },
    {
        "application":"Outlook",
        "duration":40,
        "starttime":"13:52:35"
    },
    {
        "application":"PowerPoint",
        "duration":10,
        "starttime":"13:53:15"
    },
    {
        "application":"Teams",
        "duration":290,
        "starttime":"13:53:25"
    },
    {
        "application":"Outlook",
        "duration":170,
        "starttime":"13:58:15"
    },
    {
        "application":"Chrome",
        "duration":45,
        "starttime":"14:01:05"
    },
    {
        "application":"Atom",
        "duration":5,
        "starttime":"14:01:50"
    },
    {
        "application":"Chrome",
        "duration":375,
        "starttime":"14:01:55"
    },
    {
        "application":"Finder",
        "duration":5,
        "starttime":"14:08:10"
    },
    {
        "application":"RARE",
        "duration":5,
        "starttime":"14:08:15"
    },
    {
        "application":"Slack",
        "duration":80,
        "starttime":"14:08:20"
    },
    {
        "application":"Teams",
        "duration":15,
        "starttime":"14:09:40"
    },
    {
        "application":"Chrome",
        "duration":45,
        "starttime":"14:09:55"
    },
    {
        "application":"Slack",
        "duration":80,
        "starttime":"14:10:40"
    },
    {
        "application":"Finder",
        "duration":85,
        "starttime":"14:12:00"
    },
    {
        "application":"Slack",
        "duration":235,
        "starttime":"14:13:25"
    },
    {
        "application":"Preview",
        "duration":75,
        "starttime":"14:17:20"
    },
    {
        "application":"RARE",
        "duration":10,
        "starttime":"14:18:35"
    },
    {
        "application":"Slack",
        "duration":590,
        "starttime":"14:18:45"
    },
    {
        "application":"RARE",
        "duration":5,
        "starttime":"14:28:35"
    },
    {
        "application":"Chrome",
        "duration":25,
        "starttime":"14:28:40"
    },
    {
        "application":"Atom",
        "duration":5,
        "starttime":"14:29:05"
    },
    {
        "application":"loginwindow",
        "duration":1800,
        "starttime":"14:29:10"
    },
    {
        "application":"Finder",
        "duration":70,
        "starttime":"14:59:10"
    },
    {
        "application":"loginwindow",
        "duration":725,
        "starttime":"15:00:20"
    },
    {
        "application":"Slack",
        "duration":30,
        "starttime":"15:12:25"
    },
    {
        "application":"Finder",
        "duration":15,
        "starttime":"15:12:55"
    },
    {
        "application":"Teams",
        "duration":20,
        "starttime":"15:13:10"
    },
    {
        "application":"Chrome",
        "duration":60,
        "starttime":"15:13:30"
    },
    {
        "application":"Teams",
        "duration":625,
        "starttime":"15:14:30"
    },
    {
        "application":"Slack",
        "duration":10,
        "starttime":"15:24:55"
    },
    {
        "application":"RARE",
        "duration":15,
        "starttime":"15:25:05"
    },
    {
        "application":"Chrome",
        "duration":20,
        "starttime":"15:25:20"
    },
    {
        "application":"Slack",
        "duration":670,
        "starttime":"15:25:40"
    },
    {
        "application":"Word",
        "duration":15,
        "starttime":"15:36:50"
    },
    {
        "application":"Chrome",
        "duration":30,
        "starttime":"15:37:05"
    },
    {
        "application":"Slack",
        "duration":20,
        "starttime":"15:37:35"
    },
    {
        "application":"loginwindow",
        "duration":5080,
        "starttime":"15:37:55"
    },
    {
        "application":"Atom",
        "duration":125,
        "starttime":"17:02:35"
    },
    {
        "application":"Slack",
        "duration":35,
        "starttime":"17:04:40"
    },
    {
        "application":"Teams",
        "duration":220,
        "starttime":"17:05:15"
    },
    {
        "application":"Finder",
        "duration":10,
        "starttime":"17:08:55"
    },
    {
        "application":"PowerPoint",
        "duration":5,
        "starttime":"17:09:05"
    },
    {
        "application":"Outlook",
        "duration":90,
        "starttime":"17:09:10"
    },
    {
        "application":"Excel",
        "duration":10,
        "starttime":"17:10:40"
    },
    {
        "application":"RARE",
        "duration":35,
        "starttime":"17:10:50"
    },
    {
        "application":"Preview",
        "duration":145,
        "starttime":"17:11:25"
    },
    {
        "application":"Teams",
        "duration":15,
        "starttime":"17:13:50"
    },
    {
        "application":"Chrome",
        "duration":5,
        "starttime":"17:14:05"
    },
    {
        "application":"Finder",
        "duration":35,
        "starttime":"17:14:10"
    },
    {
        "application":"Excel",
        "duration":25,
        "starttime":"17:14:45"
    },
    {
        "application":"Teams",
        "duration":25,
        "starttime":"17:15:10"
    },
    {
        "application":"Slack",
        "duration":45,
        "starttime":"17:15:35"
    },
    {
        "application":"Excel",
        "duration":25,
        "starttime":"17:16:20"
    },
    {
        "application":"zoom.us",
        "duration":95,
        "starttime":"17:16:45"
    },
    {
        "application":"Outlook",
        "duration":570,
        "starttime":"17:18:20"
    },
    {
        "application":"PowerPoint",
        "duration":95,
        "starttime":"17:27:50"
    },
    {
        "application":"Outlook",
        "duration":5,
        "starttime":"17:29:25"
    },
    {
        "application":"PowerPoint",
        "duration":10,
        "starttime":"17:29:30"
    },
    {
        "application":"Chrome",
        "duration":15,
        "starttime":"17:29:40"
    },
    {
        "application":"Slack",
        "duration":80,
        "starttime":"17:29:55"
    },
    {
        "application":"RARE",
        "duration":5,
        "starttime":"17:31:15"
    },
    {
        "application":"Outlook",
        "duration":140,
        "starttime":"17:31:20"
    },
    {
        "application":"Atom",
        "duration":50,
        "starttime":"17:33:40"
    },
    {
        "application":"Chrome",
        "duration":10,
        "starttime":"17:34:30"
    },
    {
        "application":"loginwindow",
        "duration":60,
        "starttime":"17:34:40"
    },
    {
        "application":"Outlook",
        "duration":20,
        "starttime":"17:35:40"
    },
    {
        "application":"Word",
        "duration":5,
        "starttime":"17:36:00"
    },
    {
        "application":"Outlook",
        "duration":5,
        "starttime":"17:36:05"
    },
    {
        "application":"Chrome",
        "duration":670,
        "starttime":"17:36:10"
    },
    {
        "application":"Teams",
        "duration":280,
        "starttime":"17:47:20"
    },
    {
        "application":"loginwindow",
        "duration":575,
        "starttime":"17:52:00"
    },
    {
        "application":"Atom",
        "duration":5,
        "starttime":"18:01:35"
    },
    {
        "application":"Slack",
        "duration":5,
        "starttime":"18:01:40"
    },
    {
        "application":"Chrome",
        "duration":605,
        "starttime":"18:01:45"
    },
    {
        "application":"Preview",
        "duration":530,
        "starttime":"18:11:50"
    },
    {
        "application":"PowerPoint",
        "duration":2805,
        "starttime":"18:20:40"
    },
    {
        "application":"Teams",
        "duration":15,
        "starttime":"19:07:25"
    },
    {
        "application":"Chrome",
        "duration":75,
        "starttime":"19:07:40"
    },
    {
        "application":"Slack",
        "duration":10,
        "starttime":"19:08:55"
    },
    {
        "application":"Chrome",
        "duration":565,
        "starttime":"19:09:05"
    },
    {
        "application":"Slack",
        "duration":55,
        "starttime":"19:18:30"
    },
    {
        "application":"Finder",
        "duration":30,
        "starttime":"19:19:25"
    },
    {
        "application":"Atom",
        "duration":55,
        "starttime":"19:19:55"
    },
    {
        "application":"PowerPoint",
        "duration":95,
        "starttime":"19:20:50"
    },
    {
        "application":"Chrome",
        "duration":350,
        "starttime":"19:22:25"
    },
    {
        "application":"Finder",
        "duration":45,
        "starttime":"19:28:15"
    },
    {
        "application":"Slack",
        "duration":40,
        "starttime":"19:29:00"
    },
    {
        "application":"Chrome",
        "duration":690,
        "starttime":"19:29:40"
    },
    {
        "application":"Slack",
        "duration":20,
        "starttime":"19:41:10"
    },
    {
        "application":"Outlook",
        "duration":30,
        "starttime":"19:41:30"
    },
    {
        "application":"Slack",
        "duration":35,
        "starttime":"19:42:00"
    },
    {
        "application":"Word",
        "duration":240,
        "starttime":"19:42:35"
    },
    {
        "application":"PowerPoint",
        "duration":335,
        "starttime":"19:46:35"
    },
    {
        "application":"Atom",
        "duration":925,
        "starttime":"19:52:10"
    },
    {
        "application":"Preview",
        "duration":915,
        "starttime":"20:07:35"
    },
    {
        "application":"Finder",
        "duration":30,
        "starttime":"20:22:50"
    },
    {
        "application":"Slack",
        "duration":10,
        "starttime":"20:23:20"
    },
    {
        "application":"Outlook",
        "duration":55,
        "starttime":"20:23:30"
    },
    {
        "application":"Chrome",
        "duration":220,
        "starttime":"20:24:25"
    },
    {
        "application":"Atom",
        "duration":25,
        "starttime":"20:28:05"
    },
    {
        "application":"Outlook",
        "duration":25,
        "starttime":"20:28:30"
    },
    {
        "application":"PowerPoint",
        "duration":55,
        "starttime":"20:28:55"
    },
    {
        "application":"Word",
        "duration":5,
        "starttime":"20:29:50"
    },
    {
        "application":"zoom.us",
        "duration":465,
        "starttime":"20:29:55"
    },
    {
        "application":"Word",
        "duration":260,
        "starttime":"20:37:40"
    },
    {
        "application":"Outlook",
        "duration":50,
        "starttime":"20:42:00"
    },
    {
        "application":"Atom",
        "duration":115,
        "starttime":"20:42:50"
    },
    {
        "application":"zoom.us",
        "duration":95,
        "starttime":"20:44:45"
    },
    {
        "application":"Preview",
        "duration":65,
        "starttime":"20:46:20"
    },
    {
        "application":"Chrome",
        "duration":60,
        "starttime":"20:47:25"
    },
    {
        "application":"Slack",
        "duration":115,
        "starttime":"20:48:25"
    },
    {
        "application":"RARE",
        "duration":5,
        "starttime":"20:50:20"
    },
    {
        "application":"Slack",
        "duration":55,
        "starttime":"20:50:25"
    },
    {
        "application":"PowerPoint",
        "duration":85,
        "starttime":"20:51:20"
    },
    {
        "application":"Atom",
        "duration":40,
        "starttime":"20:52:45"
    },
    {
        "application":"Slack",
        "duration":25,
        "starttime":"20:53:25"
    },
    {
        "application":"Chrome",
        "duration":70,
        "starttime":"20:53:50"
    },
    {
        "application":"Slack",
        "duration":300,
        "starttime":"20:55:00"
    },
    {
        "application":"Atom",
        "duration":40,
        "starttime":"21:00:00"
    },
    {
        "application":"Chrome",
        "duration":5,
        "starttime":"21:00:40"
    },
    {
        "application":"zoom.us",
        "duration":1055,
        "starttime":"21:00:45"
    },
    {
        "application":"Outlook",
        "duration":5,
        "starttime":"21:18:20"
    },
    {
        "application":"Word",
        "duration":5,
        "starttime":"21:18:25"
    },
    {
        "application":"Outlook",
        "duration":30,
        "starttime":"21:18:30"
    },
    {
        "application":"Chrome",
        "duration":755,
        "starttime":"21:19:00"
    },
    {
        "application":"Outlook",
        "duration":55,
        "starttime":"21:31:35"
    },
    {
        "application":"Slack",
        "duration":95,
        "starttime":"21:32:30"
    },
    {
        "application":"Chrome",
        "duration":230,
        "starttime":"21:34:05"
    },
    {
        "application":"Teams",
        "duration":5,
        "starttime":"21:37:55"
    },
    {
        "application":"Outlook",
        "duration":90,
        "starttime":"21:38:00"
    },
    {
        "application":"loginwindow",
        "duration":8430,
        "starttime":"21:39:30"
    }
]