[
    {
        "application":"loginwindow",
        "duration":2385,
        "starttime":"08:00:00"
    },
    {
        "application":"Preview",
        "duration":5,
        "starttime":"08:39:45"
    },
    {
        "application":"Teams",
        "duration":15,
        "starttime":"08:39:50"
    },
    {
        "application":"RStudio",
        "duration":5,
        "starttime":"08:40:05"
    },
    {
        "application":"loginwindow",
        "duration":5,
        "starttime":"08:40:10"
    },
    {
        "application":"Teams",
        "duration":95,
        "starttime":"08:40:15"
    },
    {
        "application":"Slack",
        "duration":10,
        "starttime":"08:41:50"
    },
    {
        "application":"RARE",
        "duration":1160,
        "starttime":"08:42:00"
    },
    {
        "application":"Chrome",
        "duration":1020,
        "starttime":"09:01:20"
    },
    {
        "application":"RARE",
        "duration":20,
        "starttime":"09:18:20"
    },
    {
        "application":"iTerm2",
        "duration":35,
        "starttime":"09:18:40"
    },
    {
        "application":"Slack",
        "duration":5,
        "starttime":"09:19:15"
    },
    {
        "application":"iTerm2",
        "duration":40,
        "starttime":"09:19:20"
    },
    {
        "application":"Slack",
        "duration":15,
        "starttime":"09:20:00"
    },
    {
        "application":"RARE",
        "duration":10,
        "starttime":"09:20:15"
    },
    {
        "application":"Finder",
        "duration":30,
        "starttime":"09:20:25"
    },
    {
        "application":"Chrome",
        "duration":15,
        "starttime":"09:20:55"
    },
    {
        "application":"RARE",
        "duration":705,
        "starttime":"09:21:10"
    },
    {
        "application":"Preview",
        "duration":5,
        "starttime":"09:32:55"
    },
    {
        "application":"Finder",
        "duration":25,
        "starttime":"09:33:00"
    },
    {
        "application":"Preview",
        "duration":95,
        "starttime":"09:33:25"
    },
    {
        "application":"iTerm2",
        "duration":30,
        "starttime":"09:35:00"
    },
    {
        "application":"RStudio",
        "duration":5,
        "starttime":"09:35:30"
    },
    {
        "application":"Preview",
        "duration":5,
        "starttime":"09:35:35"
    },
    {
        "application":"Teams",
        "duration":90,
        "starttime":"09:35:40"
    },
    {
        "application":"Outlook",
        "duration":30,
        "starttime":"09:37:10"
    },
    {
        "application":"Chrome",
        "duration":45,
        "starttime":"09:37:40"
    },
    {
        "application":"RStudio",
        "duration":95,
        "starttime":"09:38:25"
    },
    {
        "application":"Slack",
        "duration":50,
        "starttime":"09:40:00"
    },
    {
        "application":"RARE",
        "duration":5,
        "starttime":"09:40:50"
    },
    {
        "application":"Slack",
        "duration":15,
        "starttime":"09:40:55"
    },
    {
        "application":"Chrome",
        "duration":5,
        "starttime":"09:41:10"
    },
    {
        "application":"Preview",
        "duration":100,
        "starttime":"09:41:15"
    },
    {
        "application":"iTerm2",
        "duration":5,
        "starttime":"09:42:55"
    },
    {
        "application":"Finder",
        "duration":5,
        "starttime":"09:43:00"
    },
    {
        "application":"Atom",
        "duration":80,
        "starttime":"09:43:05"
    },
    {
        "application":"Outlook",
        "duration":50,
        "starttime":"09:44:25"
    },
    {
        "application":"RARE",
        "duration":25,
        "starttime":"09:45:15"
    },
    {
        "application":"Slack",
        "duration":5,
        "starttime":"09:45:40"
    },
    {
        "application":"Chrome",
        "duration":5,
        "starttime":"09:45:45"
    },
    {
        "application":"Slack",
        "duration":330,
        "starttime":"09:45:50"
    },
    {
        "application":"Chrome",
        "duration":40,
        "starttime":"09:51:20"
    },
    {
        "application":"RStudio",
        "duration":5,
        "starttime":"09:52:00"
    },
    {
        "application":"Atom",
        "duration":25,
        "starttime":"09:52:05"
    },
    {
        "application":"RStudio",
        "duration":5,
        "starttime":"09:52:30"
    },
    {
        "application":"Chrome",
        "duration":15,
        "starttime":"09:52:35"
    },
    {
        "application":"Preview",
        "duration":60,
        "starttime":"09:52:50"
    },
    {
        "application":"RARE",
        "duration":5,
        "starttime":"09:53:50"
    },
    {
        "application":"Preview",
        "duration":10,
        "starttime":"09:53:55"
    },
    {
        "application":"Chrome",
        "duration":20,
        "starttime":"09:54:05"
    },
    {
        "application":"RARE",
        "duration":5,
        "starttime":"09:54:25"
    },
    {
        "application":"Chrome",
        "duration":40,
        "starttime":"09:54:30"
    },
    {
        "application":"Slack",
        "duration":330,
        "starttime":"09:55:10"
    },
    {
        "application":"Preview",
        "duration":85,
        "starttime":"10:00:40"
    },
    {
        "application":"loginwindow",
        "duration":20,
        "starttime":"10:02:05"
    },
    {
        "application":"RARE",
        "duration":15,
        "starttime":"10:02:25"
    },
    {
        "application":"MacDown",
        "duration":165,
        "starttime":"10:02:40"
    },
    {
        "application":"Preview",
        "duration":30,
        "starttime":"10:05:25"
    },
    {
        "application":"Atom",
        "duration":45,
        "starttime":"10:05:55"
    },
    {
        "application":"Finder",
        "duration":5,
        "starttime":"10:06:40"
    },
    {
        "application":"Chrome",
        "duration":220,
        "starttime":"10:06:45"
    },
    {
        "application":"Teams",
        "duration":735,
        "starttime":"10:10:25"
    },
    {
        "application":"Preview",
        "duration":5,
        "starttime":"10:22:40"
    },
    {
        "application":"Finder",
        "duration":5,
        "starttime":"10:22:45"
    },
    {
        "application":"Atom",
        "duration":5,
        "starttime":"10:22:50"
    },
    {
        "application":"Teams",
        "duration":155,
        "starttime":"10:22:55"
    },
    {
        "application":"Preview",
        "duration":180,
        "starttime":"10:25:30"
    },
    {
        "application":"Slack",
        "duration":5,
        "starttime":"10:28:30"
    },
    {
        "application":"RARE",
        "duration":30,
        "starttime":"10:28:35"
    },
    {
        "application":"Atom",
        "duration":5,
        "starttime":"10:29:05"
    },
    {
        "application":"Teams",
        "duration":60,
        "starttime":"10:29:10"
    },
    {
        "application":"Atom",
        "duration":265,
        "starttime":"10:30:10"
    },
    {
        "application":"RARE",
        "duration":5,
        "starttime":"10:34:35"
    },
    {
        "application":"Chrome",
        "duration":30,
        "starttime":"10:34:40"
    },
    {
        "application":"Outlook",
        "duration":10,
        "starttime":"10:35:10"
    },
    {
        "application":"Atom",
        "duration":45,
        "starttime":"10:35:20"
    },
    {
        "application":"Slack",
        "duration":5,
        "starttime":"10:36:05"
    },
    {
        "application":"RARE",
        "duration":80,
        "starttime":"10:36:10"
    },
    {
        "application":"Slack",
        "duration":55,
        "starttime":"10:37:30"
    },
    {
        "application":"Chrome",
        "duration":105,
        "starttime":"10:38:25"
    },
    {
        "application":"Teams",
        "duration":95,
        "starttime":"10:40:10"
    },
    {
        "application":"RARE",
        "duration":5,
        "starttime":"10:41:45"
    },
    {
        "application":"Atom",
        "duration":95,
        "starttime":"10:41:50"
    },
    {
        "application":"Preview",
        "duration":5,
        "starttime":"10:43:25"
    },
    {
        "application":"Teams",
        "duration":210,
        "starttime":"10:43:30"
    },
    {
        "application":"RARE",
        "duration":15,
        "starttime":"10:47:00"
    },
    {
        "application":"RStudio",
        "duration":35,
        "starttime":"10:47:15"
    },
    {
        "application":"RARE",
        "duration":80,
        "starttime":"10:47:50"
    },
    {
        "application":"Preview",
        "duration":1635,
        "starttime":"10:49:10"
    },
    {
        "application":"RARE",
        "duration":5,
        "starttime":"11:16:25"
    },
    {
        "application":"Chrome",
        "duration":5,
        "starttime":"11:16:30"
    },
    {
        "application":"Atom",
        "duration":210,
        "starttime":"11:16:35"
    },
    {
        "application":"Chrome",
        "duration":20,
        "starttime":"11:20:05"
    },
    {
        "application":"Atom",
        "duration":1485,
        "starttime":"11:20:25"
    },
    {
        "application":"RStudio",
        "duration":195,
        "starttime":"11:45:10"
    },
    {
        "application":"Atom",
        "duration":120,
        "starttime":"11:48:25"
    },
    {
        "application":"RARE",
        "duration":5,
        "starttime":"11:50:25"
    },
    {
        "application":"Atom",
        "duration":40,
        "starttime":"11:50:30"
    },
    {
        "application":"Teams",
        "duration":5,
        "starttime":"11:51:10"
    },
    {
        "application":"Atom",
        "duration":565,
        "starttime":"11:51:15"
    },
    {
        "application":"Outlook",
        "duration":20,
        "starttime":"12:00:40"
    },
    {
        "application":"Atom",
        "duration":125,
        "starttime":"12:01:00"
    },
    {
        "application":"MacDown",
        "duration":25,
        "starttime":"12:03:05"
    },
    {
        "application":"Atom",
        "duration":1780,
        "starttime":"12:03:30"
    },
    {
        "application":"Outlook",
        "duration":10,
        "starttime":"12:33:10"
    },
    {
        "application":"Atom",
        "duration":380,
        "starttime":"12:33:20"
    },
    {
        "application":"Preview",
        "duration":270,
        "starttime":"12:39:40"
    },
    {
        "application":"Atom",
        "duration":420,
        "starttime":"12:44:10"
    },
    {
        "application":"Finder",
        "duration":5,
        "starttime":"12:51:10"
    },
    {
        "application":"Teams",
        "duration":5,
        "starttime":"12:51:15"
    },
    {
        "application":"RARE",
        "duration":480,
        "starttime":"12:51:20"
    },
    {
        "application":"Atom",
        "duration":10,
        "starttime":"12:59:20"
    },
    {
        "application":"Teams",
        "duration":70,
        "starttime":"12:59:30"
    },
    {
        "application":"Atom",
        "duration":420,
        "starttime":"13:00:40"
    },
    {
        "application":"Slack",
        "duration":5,
        "starttime":"13:07:40"
    },
    {
        "application":"Atom",
        "duration":840,
        "starttime":"13:07:45"
    },
    {
        "application":"Preview",
        "duration":5,
        "starttime":"13:21:45"
    },
    {
        "application":"Atom",
        "duration":2260,
        "starttime":"13:21:50"
    },
    {
        "application":"RARE",
        "duration":35,
        "starttime":"13:59:30"
    },
    {
        "application":"Atom",
        "duration":1600,
        "starttime":"14:00:05"
    },
    {
        "application":"iTerm2",
        "duration":10,
        "starttime":"14:26:45"
    },
    {
        "application":"RARE",
        "duration":25,
        "starttime":"14:26:55"
    },
    {
        "application":"Atom",
        "duration":190,
        "starttime":"14:27:20"
    },
    {
        "application":"iTerm2",
        "duration":5,
        "starttime":"14:30:30"
    },
    {
        "application":"Chrome",
        "duration":15,
        "starttime":"14:30:35"
    },
    {
        "application":"RARE",
        "duration":5,
        "starttime":"14:30:50"
    },
    {
        "application":"Atom",
        "duration":70,
        "starttime":"14:30:55"
    },
    {
        "application":"iTerm2",
        "duration":15,
        "starttime":"14:32:05"
    },
    {
        "application":"Chrome",
        "duration":20,
        "starttime":"14:32:20"
    },
    {
        "application":"Atom",
        "duration":615,
        "starttime":"14:32:40"
    },
    {
        "application":"Finder",
        "duration":95,
        "starttime":"14:42:55"
    },
    {
        "application":"Atom",
        "duration":965,
        "starttime":"14:44:30"
    },
    {
        "application":"Teams",
        "duration":5,
        "starttime":"15:00:35"
    },
    {
        "application":"Chrome",
        "duration":75,
        "starttime":"15:00:40"
    },
    {
        "application":"RARE",
        "duration":10,
        "starttime":"15:01:55"
    },
    {
        "application":"MacDown",
        "duration":120,
        "starttime":"15:02:05"
    },
    {
        "application":"Finder",
        "duration":5,
        "starttime":"15:04:05"
    },
    {
        "application":"Atom",
        "duration":5,
        "starttime":"15:04:10"
    },
    {
        "application":"Slack",
        "duration":15,
        "starttime":"15:04:15"
    },
    {
        "application":"RStudio",
        "duration":5,
        "starttime":"15:04:30"
    },
    {
        "application":"Outlook",
        "duration":275,
        "starttime":"15:04:35"
    },
    {
        "application":"RARE",
        "duration":5,
        "starttime":"15:09:10"
    },
    {
        "application":"Chrome",
        "duration":5,
        "starttime":"15:09:15"
    },
    {
        "application":"Slack",
        "duration":15,
        "starttime":"15:09:20"
    },
    {
        "application":"Outlook",
        "duration":5,
        "starttime":"15:09:35"
    },
    {
        "application":"Slack",
        "duration":15,
        "starttime":"15:09:40"
    },
    {
        "application":"Outlook",
        "duration":45,
        "starttime":"15:09:55"
    },
    {
        "application":"Finder",
        "duration":5,
        "starttime":"15:10:40"
    },
    {
        "application":"Preview",
        "duration":1000,
        "starttime":"15:10:45"
    },
    {
        "application":"Slack",
        "duration":30,
        "starttime":"15:27:25"
    },
    {
        "application":"Teams",
        "duration":5,
        "starttime":"15:27:55"
    },
    {
        "application":"Slack",
        "duration":60,
        "starttime":"15:28:00"
    },
    {
        "application":"Chrome",
        "duration":540,
        "starttime":"15:29:00"
    },
    {
        "application":"Preview",
        "duration":265,
        "starttime":"15:38:00"
    },
    {
        "application":"Slack",
        "duration":5,
        "starttime":"15:42:25"
    },
    {
        "application":"Preview",
        "duration":60,
        "starttime":"15:42:30"
    },
    {
        "application":"Teams",
        "duration":5,
        "starttime":"15:43:30"
    },
    {
        "application":"RARE",
        "duration":20,
        "starttime":"15:43:35"
    },
    {
        "application":"Slack",
        "duration":115,
        "starttime":"15:43:55"
    },
    {
        "application":"Preview",
        "duration":10,
        "starttime":"15:45:50"
    },
    {
        "application":"Chrome",
        "duration":20,
        "starttime":"15:46:00"
    },
    {
        "application":"Teams",
        "duration":30,
        "starttime":"15:46:20"
    },
    {
        "application":"RARE",
        "duration":5,
        "starttime":"15:46:50"
    },
    {
        "application":"Finder",
        "duration":5,
        "starttime":"15:46:55"
    },
    {
        "application":"Slack",
        "duration":45,
        "starttime":"15:47:00"
    },
    {
        "application":"RStudio",
        "duration":290,
        "starttime":"15:47:45"
    },
    {
        "application":"Chrome",
        "duration":145,
        "starttime":"15:52:35"
    },
    {
        "application":"Atom",
        "duration":25,
        "starttime":"15:55:00"
    },
    {
        "application":"Preview",
        "duration":140,
        "starttime":"15:55:25"
    },
    {
        "application":"Chrome",
        "duration":110,
        "starttime":"15:57:45"
    },
    {
        "application":"Atom",
        "duration":20,
        "starttime":"15:59:35"
    },
    {
        "application":"MacDown",
        "duration":240,
        "starttime":"15:59:55"
    },
    {
        "application":"Atom",
        "duration":385,
        "starttime":"16:03:55"
    },
    {
        "application":"RStudio",
        "duration":20,
        "starttime":"16:10:20"
    },
    {
        "application":"Atom",
        "duration":305,
        "starttime":"16:10:40"
    },
    {
        "application":"Preview",
        "duration":10,
        "starttime":"16:15:45"
    },
    {
        "application":"Slack",
        "duration":60,
        "starttime":"16:15:55"
    },
    {
        "application":"Atom",
        "duration":2255,
        "starttime":"16:16:55"
    },
    {
        "application":"RARE",
        "duration":5,
        "starttime":"16:54:30"
    },
    {
        "application":"Chrome",
        "duration":20,
        "starttime":"16:54:35"
    },
    {
        "application":"Finder",
        "duration":5,
        "starttime":"16:54:55"
    },
    {
        "application":"Chrome",
        "duration":15,
        "starttime":"16:55:00"
    },
    {
        "application":"Atom",
        "duration":255,
        "starttime":"16:55:15"
    },
    {
        "application":"Outlook",
        "duration":50,
        "starttime":"16:59:30"
    },
    {
        "application":"Slack",
        "duration":85,
        "starttime":"17:00:20"
    },
    {
        "application":"loginwindow",
        "duration":105,
        "starttime":"17:01:45"
    },
    {
        "application":"Chrome",
        "duration":20,
        "starttime":"17:03:30"
    },
    {
        "application":"Atom",
        "duration":40,
        "starttime":"17:03:50"
    },
    {
        "application":"Outlook",
        "duration":55,
        "starttime":"17:04:30"
    },
    {
        "application":"iTerm2",
        "duration":40,
        "starttime":"17:05:25"
    },
    {
        "application":"Atom",
        "duration":10,
        "starttime":"17:06:05"
    },
    {
        "application":"RARE",
        "duration":70,
        "starttime":"17:06:15"
    },
    {
        "application":"Atom",
        "duration":25,
        "starttime":"17:07:25"
    },
    {
        "application":"Outlook",
        "duration":15,
        "starttime":"17:07:50"
    },
    {
        "application":"Atom",
        "duration":230,
        "starttime":"17:08:05"
    },
    {
        "application":"RStudio",
        "duration":65,
        "starttime":"17:11:55"
    },
    {
        "application":"Atom",
        "duration":985,
        "starttime":"17:13:00"
    },
    {
        "application":"Preview",
        "duration":15,
        "starttime":"17:29:25"
    },
    {
        "application":"Slack",
        "duration":25,
        "starttime":"17:29:40"
    },
    {
        "application":"RARE",
        "duration":260,
        "starttime":"17:30:05"
    },
    {
        "application":"Outlook",
        "duration":5,
        "starttime":"17:34:25"
    },
    {
        "application":"Atom",
        "duration":30,
        "starttime":"17:34:30"
    },
    {
        "application":"Chrome",
        "duration":55,
        "starttime":"17:35:00"
    },
    {
        "application":"Outlook",
        "duration":15,
        "starttime":"17:35:55"
    },
    {
        "application":"iTerm2",
        "duration":15,
        "starttime":"17:36:10"
    },
    {
        "application":"Atom",
        "duration":30,
        "starttime":"17:36:25"
    },
    {
        "application":"Preview",
        "duration":130,
        "starttime":"17:36:55"
    },
    {
        "application":"Atom",
        "duration":1060,
        "starttime":"17:39:05"
    },
    {
        "application":"loginwindow",
        "duration":21795,
        "starttime":"17:56:45"
    }
]